<?xml version="1.0" encoding="utf-8"?>
<DvbCableService xmlns:xsi="http://www.w3.org/2001/XMLSchema-instance" xmlns:xsd="http://www.w3.org/2001/XMLSchema">
  <Name>DIGI TV</Name>
  <ShortName>DIGITV</ShortName>
  <Transponders>
    <TuningInfoDvbC frequency="114500000" system="DVB-C" modulation="64-QAM" inversion="auto" symbolrate="6000000" FEC="auto" />
    <TuningInfoDvbC frequency="121500000" system="DVB-C" modulation="64-QAM" inversion="auto" symbolrate="6000000" FEC="auto" />
    <TuningInfoDvbC frequency="128500000" system="DVB-C" modulation="64-QAM" inversion="auto" symbolrate="6000000" FEC="auto" />
    <TuningInfoDvbC frequency="135500000" system="DVB-C" modulation="64-QAM" inversion="auto" symbolrate="6000000" FEC="auto" />
    <TuningInfoDvbC frequency="354000000" system="DVB-C" modulation="64-QAM" inversion="auto" symbolrate="6900000" FEC="auto" />
    <TuningInfoDvbC frequency="362000000" system="DVB-C" modulation="64-QAM" inversion="auto" symbolrate="6900000" FEC="auto" />
    <TuningInfoDvbC frequency="370000000" system="DVB-C" modulation="64-QAM" inversion="auto" symbolrate="6900000" FEC="auto" />
    <TuningInfoDvbC frequency="386000000" system="DVB-C" modulation="64-QAM" inversion="auto" symbolrate="6900000" FEC="auto" />
    <TuningInfoDvbC frequency="394000000" system="DVB-C" modulation="64-QAM" inversion="auto" symbolrate="6900000" FEC="auto" />
    <TuningInfoDvbC frequency="402000000" system="DVB-C" modulation="64-QAM" inversion="auto" symbolrate="6900000" FEC="auto" />
    <TuningInfoDvbC frequency="410000000" system="DVB-C" modulation="64-QAM" inversion="auto" symbolrate="6900000" FEC="auto" />
    <TuningInfoDvbC frequency="722000000" system="DVB-C" modulation="64-QAM" inversion="auto" symbolrate="6900000" FEC="auto" />
    <TuningInfoDvbC frequency="730000000" system="DVB-C" modulation="64-QAM" inversion="auto" symbolrate="6900000" FEC="auto" />
    <TuningInfoDvbC frequency="738000000" system="DVB-C" modulation="64-QAM" inversion="auto" symbolrate="6900000" FEC="auto" />
    <TuningInfoDvbC frequency="746000000" system="DVB-C" modulation="64-QAM" inversion="auto" symbolrate="6900000" FEC="auto" />
    <TuningInfoDvbC frequency="762000000" system="DVB-C" modulation="64-QAM" inversion="auto" symbolrate="6900000" FEC="auto" />
    <TuningInfoDvbC frequency="770000000" system="DVB-C" modulation="64-QAM" inversion="auto" symbolrate="6900000" FEC="auto" />
    <TuningInfoDvbC frequency="778000000" system="DVB-C" modulation="64-QAM" inversion="auto" symbolrate="6900000" FEC="auto" />
    <TuningInfoDvbC frequency="786000000" system="DVB-C" modulation="64-QAM" inversion="auto" symbolrate="6900000" FEC="auto" />
  </Transponders>
  <CountryCode>HU</CountryCode>
</DvbCableService>