<?xml version="1.0" encoding="utf-8"?>
<Satellite xmlns:xsi="http://www.w3.org/2001/XMLSchema-instance" xmlns:xsd="http://www.w3.org/2001/XMLSchema">
  <Name>NSS-7</Name>
  <ShortName>20.0W</ShortName>
  <Transponders>
    <TuningInfoDvbS frequency="3969000000" system="DVB-S" modulation="QPSK" inversion="auto" satnumber="0" symbolrate="3410000" polarity="right" FEC="3/4" rolloff="auto" pilots="auto">
      <LnbLow>0</LnbLow>
      <LnbHigh>0</LnbHigh>
      <LnbSwitch>0</LnbSwitch>
    </TuningInfoDvbS>
    <TuningInfoDvbS frequency="3973000000" system="DVB-S" modulation="QPSK" inversion="auto" satnumber="0" symbolrate="3410000" polarity="right" FEC="3/4" rolloff="auto" pilots="auto">
      <LnbLow>0</LnbLow>
      <LnbHigh>0</LnbHigh>
      <LnbSwitch>0</LnbSwitch>
    </TuningInfoDvbS>
    <TuningInfoDvbS frequency="3977000000" system="DVB-S" modulation="QPSK" inversion="auto" satnumber="0" symbolrate="3410000" polarity="right" FEC="3/4" rolloff="auto" pilots="auto">
      <LnbLow>0</LnbLow>
      <LnbHigh>0</LnbHigh>
      <LnbSwitch>0</LnbSwitch>
    </TuningInfoDvbS>
    <TuningInfoDvbS frequency="4130000000" system="DVB-S2" modulation="QPSK" inversion="auto" satnumber="0" symbolrate="12122000" polarity="right" FEC="1/2" rolloff="auto" pilots="auto">
      <LnbLow>0</LnbLow>
      <LnbHigh>0</LnbHigh>
      <LnbSwitch>0</LnbSwitch>
    </TuningInfoDvbS>
    <TuningInfoDvbS frequency="11549000000" system="DVB-S" modulation="QPSK" inversion="auto" satnumber="0" symbolrate="2790000" polarity="horizontal" FEC="7/8" rolloff="auto" pilots="auto">
      <LnbLow>0</LnbLow>
      <LnbHigh>0</LnbHigh>
      <LnbSwitch>0</LnbSwitch>
    </TuningInfoDvbS>
    <TuningInfoDvbS frequency="11585000000" system="DVB-S" modulation="QPSK" inversion="auto" satnumber="0" symbolrate="2200000" polarity="horizontal" FEC="1/2" rolloff="auto" pilots="auto">
      <LnbLow>0</LnbLow>
      <LnbHigh>0</LnbHigh>
      <LnbSwitch>0</LnbSwitch>
    </TuningInfoDvbS>
    <TuningInfoDvbS frequency="12636000000" system="DVB-S2" modulation="QPSK" inversion="auto" satnumber="0" symbolrate="4924000" polarity="horizontal" FEC="3/4" rolloff="auto" pilots="auto">
      <LnbLow>0</LnbLow>
      <LnbHigh>0</LnbHigh>
      <LnbSwitch>0</LnbSwitch>
    </TuningInfoDvbS>
    <TuningInfoDvbS frequency="12642000000" system="DVB-S2" modulation="QPSK" inversion="auto" satnumber="0" symbolrate="4750000" polarity="horizontal" FEC="5/6" rolloff="auto" pilots="auto">
      <LnbLow>0</LnbLow>
      <LnbHigh>0</LnbHigh>
      <LnbSwitch>0</LnbSwitch>
    </TuningInfoDvbS>
    <TuningInfoDvbS frequency="12648000000" system="DVB-S2" modulation="QPSK" inversion="auto" satnumber="0" symbolrate="4167000" polarity="horizontal" FEC="5/6" rolloff="auto" pilots="auto">
      <LnbLow>0</LnbLow>
      <LnbHigh>0</LnbHigh>
      <LnbSwitch>0</LnbSwitch>
    </TuningInfoDvbS>
    <TuningInfoDvbS frequency="12654000000" system="DVB-S2" modulation="QPSK" inversion="auto" satnumber="0" symbolrate="4167000" polarity="horizontal" FEC="5/6" rolloff="auto" pilots="auto">
      <LnbLow>0</LnbLow>
      <LnbHigh>0</LnbHigh>
      <LnbSwitch>0</LnbSwitch>
    </TuningInfoDvbS>
    <TuningInfoDvbS frequency="12660000000" system="DVB-S2" modulation="QPSK" inversion="auto" satnumber="0" symbolrate="4167000" polarity="horizontal" FEC="5/6" rolloff="auto" pilots="auto">
      <LnbLow>0</LnbLow>
      <LnbHigh>0</LnbHigh>
      <LnbSwitch>0</LnbSwitch>
    </TuningInfoDvbS>
    <TuningInfoDvbS frequency="12666000000" system="DVB-S2" modulation="QPSK" inversion="auto" satnumber="0" symbolrate="4600000" polarity="horizontal" FEC="5/6" rolloff="auto" pilots="auto">
      <LnbLow>0</LnbLow>
      <LnbHigh>0</LnbHigh>
      <LnbSwitch>0</LnbSwitch>
    </TuningInfoDvbS>
    <TuningInfoDvbS frequency="12672000000" system="DVB-S2" modulation="QPSK" inversion="auto" satnumber="0" symbolrate="4600000" polarity="horizontal" FEC="3/4" rolloff="auto" pilots="auto">
      <LnbLow>0</LnbLow>
      <LnbHigh>0</LnbHigh>
      <LnbSwitch>0</LnbSwitch>
    </TuningInfoDvbS>
    <TuningInfoDvbS frequency="12683000000" system="DVB-S2" modulation="QPSK" inversion="auto" satnumber="0" symbolrate="7200000" polarity="horizontal" FEC="3/4" rolloff="auto" pilots="auto">
      <LnbLow>0</LnbLow>
      <LnbHigh>0</LnbHigh>
      <LnbSwitch>0</LnbSwitch>
    </TuningInfoDvbS>
    <TuningInfoDvbS frequency="12734000000" system="DVB-S2" modulation="8-PSK" inversion="auto" satnumber="0" symbolrate="1500000" polarity="horizontal" FEC="3/4" rolloff="auto" pilots="auto">
      <LnbLow>0</LnbLow>
      <LnbHigh>0</LnbHigh>
      <LnbSwitch>0</LnbSwitch>
    </TuningInfoDvbS>
  </Transponders>
  <PositionKey>-200</PositionKey>
  <WesternOffset xsi:nil="true" />
  <EasternOffset xsi:nil="true" />
  <IsCBand>false</IsCBand>
</Satellite>