<?xml version="1.0" encoding="utf-8"?>
<Satellite xmlns:xsi="http://www.w3.org/2001/XMLSchema-instance" xmlns:xsd="http://www.w3.org/2001/XMLSchema">
  <Name>Galaxy-16</Name>
  <ShortName>99.2W</ShortName>
  <Transponders>
    <TuningInfoDvbS frequency="3720000000" system="DVB-S2" modulation="8-PSK" inversion="auto" satnumber="0" symbolrate="8700000" polarity="horizontal" FEC="3/4" rolloff="auto" pilots="auto">
      <LnbLow>0</LnbLow>
      <LnbHigh>0</LnbHigh>
      <LnbSwitch>0</LnbSwitch>
    </TuningInfoDvbS>
    <TuningInfoDvbS frequency="3735000000" system="DVB-S" modulation="QPSK" inversion="auto" satnumber="0" symbolrate="3775000" polarity="horizontal" FEC="3/4" rolloff="auto" pilots="auto">
      <LnbLow>0</LnbLow>
      <LnbHigh>0</LnbHigh>
      <LnbSwitch>0</LnbSwitch>
    </TuningInfoDvbS>
    <TuningInfoDvbS frequency="3740000000" system="DVB-S2" modulation="QPSK" inversion="auto" satnumber="0" symbolrate="30000000" polarity="vertical" FEC="5/6" rolloff="auto" pilots="auto">
      <LnbLow>0</LnbLow>
      <LnbHigh>0</LnbHigh>
      <LnbSwitch>0</LnbSwitch>
    </TuningInfoDvbS>
    <TuningInfoDvbS frequency="3776000000" system="DVB-S" modulation="QPSK" inversion="auto" satnumber="0" symbolrate="3255000" polarity="horizontal" FEC="3/4" rolloff="auto" pilots="auto">
      <LnbLow>0</LnbLow>
      <LnbHigh>0</LnbHigh>
      <LnbSwitch>0</LnbSwitch>
    </TuningInfoDvbS>
    <TuningInfoDvbS frequency="3785000000" system="DVB-S2" modulation="8-PSK" inversion="auto" satnumber="0" symbolrate="4850000" polarity="horizontal" FEC="3/4" rolloff="auto" pilots="auto">
      <LnbLow>0</LnbLow>
      <LnbHigh>0</LnbHigh>
      <LnbSwitch>0</LnbSwitch>
    </TuningInfoDvbS>
    <TuningInfoDvbS frequency="3789000000" system="DVB-S" modulation="QPSK" inversion="auto" satnumber="0" symbolrate="1666000" polarity="horizontal" FEC="5/6" rolloff="auto" pilots="auto">
      <LnbLow>0</LnbLow>
      <LnbHigh>0</LnbHigh>
      <LnbSwitch>0</LnbSwitch>
    </TuningInfoDvbS>
    <TuningInfoDvbS frequency="3791000000" system="DVB-S" modulation="QPSK" inversion="auto" satnumber="0" symbolrate="1665000" polarity="horizontal" FEC="5/6" rolloff="auto" pilots="auto">
      <LnbLow>0</LnbLow>
      <LnbHigh>0</LnbHigh>
      <LnbSwitch>0</LnbSwitch>
    </TuningInfoDvbS>
    <TuningInfoDvbS frequency="3793000000" system="DVB-S2" modulation="QPSK" inversion="auto" satnumber="0" symbolrate="7030000" polarity="vertical" FEC="1/2" rolloff="auto" pilots="auto">
      <LnbLow>0</LnbLow>
      <LnbHigh>0</LnbHigh>
      <LnbSwitch>0</LnbSwitch>
    </TuningInfoDvbS>
    <TuningInfoDvbS frequency="3810000000" system="DVB-S" modulation="QPSK" inversion="auto" satnumber="0" symbolrate="3255000" polarity="horizontal" FEC="3/4" rolloff="auto" pilots="auto">
      <LnbLow>0</LnbLow>
      <LnbHigh>0</LnbHigh>
      <LnbSwitch>0</LnbSwitch>
    </TuningInfoDvbS>
    <TuningInfoDvbS frequency="3820000000" system="DVB-S" modulation="QPSK" inversion="auto" satnumber="0" symbolrate="26000000" polarity="vertical" FEC="3/4" rolloff="auto" pilots="auto">
      <LnbLow>0</LnbLow>
      <LnbHigh>0</LnbHigh>
      <LnbSwitch>0</LnbSwitch>
    </TuningInfoDvbS>
    <TuningInfoDvbS frequency="3848000000" system="DVB-S" modulation="QPSK" inversion="auto" satnumber="0" symbolrate="15030000" polarity="horizontal" FEC="3/4" rolloff="auto" pilots="auto">
      <LnbLow>0</LnbLow>
      <LnbHigh>0</LnbHigh>
      <LnbSwitch>0</LnbSwitch>
    </TuningInfoDvbS>
    <TuningInfoDvbS frequency="3880000000" system="DVB-S2" modulation="QPSK" inversion="auto" satnumber="0" symbolrate="30000000" polarity="horizontal" FEC="5/6" rolloff="auto" pilots="auto">
      <LnbLow>0</LnbLow>
      <LnbHigh>0</LnbHigh>
      <LnbSwitch>0</LnbSwitch>
    </TuningInfoDvbS>
    <TuningInfoDvbS frequency="3900000000" system="DVB-S" modulation="QPSK" inversion="auto" satnumber="0" symbolrate="28000000" polarity="vertical" FEC="3/4" rolloff="auto" pilots="auto">
      <LnbLow>0</LnbLow>
      <LnbHigh>0</LnbHigh>
      <LnbSwitch>0</LnbSwitch>
    </TuningInfoDvbS>
    <TuningInfoDvbS frequency="3904000000" system="DVB-S" modulation="QPSK" inversion="auto" satnumber="0" symbolrate="3125000" polarity="horizontal" FEC="7/8" rolloff="auto" pilots="auto">
      <LnbLow>0</LnbLow>
      <LnbHigh>0</LnbHigh>
      <LnbSwitch>0</LnbSwitch>
    </TuningInfoDvbS>
    <TuningInfoDvbS frequency="3912000000" system="DVB-S2" modulation="8-PSK" inversion="auto" satnumber="0" symbolrate="10833000" polarity="horizontal" FEC="8/9" rolloff="auto" pilots="auto">
      <LnbLow>0</LnbLow>
      <LnbHigh>0</LnbHigh>
      <LnbSwitch>0</LnbSwitch>
    </TuningInfoDvbS>
    <TuningInfoDvbS frequency="3924000000" system="DVB-S" modulation="QPSK" inversion="auto" satnumber="0" symbolrate="3125000" polarity="horizontal" FEC="7/8" rolloff="auto" pilots="auto">
      <LnbLow>0</LnbLow>
      <LnbHigh>0</LnbHigh>
      <LnbSwitch>0</LnbSwitch>
    </TuningInfoDvbS>
    <TuningInfoDvbS frequency="3925000000" system="DVB-S" modulation="QPSK" inversion="auto" satnumber="0" symbolrate="3979000" polarity="vertical" FEC="2/3" rolloff="auto" pilots="auto">
      <LnbLow>0</LnbLow>
      <LnbHigh>0</LnbHigh>
      <LnbSwitch>0</LnbSwitch>
    </TuningInfoDvbS>
    <TuningInfoDvbS frequency="3928000000" system="DVB-S" modulation="QPSK" inversion="auto" satnumber="0" symbolrate="3125000" polarity="horizontal" FEC="7/8" rolloff="auto" pilots="auto">
      <LnbLow>0</LnbLow>
      <LnbHigh>0</LnbHigh>
      <LnbSwitch>0</LnbSwitch>
    </TuningInfoDvbS>
    <TuningInfoDvbS frequency="3930000000" system="DVB-S" modulation="QPSK" inversion="auto" satnumber="0" symbolrate="3680000" polarity="vertical" FEC="2/3" rolloff="auto" pilots="auto">
      <LnbLow>0</LnbLow>
      <LnbHigh>0</LnbHigh>
      <LnbSwitch>0</LnbSwitch>
    </TuningInfoDvbS>
    <TuningInfoDvbS frequency="3931000000" system="DVB-S" modulation="QPSK" inversion="auto" satnumber="0" symbolrate="1562000" polarity="horizontal" FEC="5/6" rolloff="auto" pilots="auto">
      <LnbLow>0</LnbLow>
      <LnbHigh>0</LnbHigh>
      <LnbSwitch>0</LnbSwitch>
    </TuningInfoDvbS>
    <TuningInfoDvbS frequency="3935000000" system="DVB-S" modulation="QPSK" inversion="auto" satnumber="0" symbolrate="1666000" polarity="horizontal" FEC="7/8" rolloff="auto" pilots="auto">
      <LnbLow>0</LnbLow>
      <LnbHigh>0</LnbHigh>
      <LnbSwitch>0</LnbSwitch>
    </TuningInfoDvbS>
    <TuningInfoDvbS frequency="3938000000" system="DVB-S" modulation="QPSK" inversion="auto" satnumber="0" symbolrate="1561000" polarity="horizontal" FEC="7/8" rolloff="auto" pilots="auto">
      <LnbLow>0</LnbLow>
      <LnbHigh>0</LnbHigh>
      <LnbSwitch>0</LnbSwitch>
    </TuningInfoDvbS>
    <TuningInfoDvbS frequency="3940000000" system="DVB-S2" modulation="QPSK" inversion="auto" satnumber="0" symbolrate="27600000" polarity="vertical" FEC="5/6" rolloff="auto" pilots="auto">
      <LnbLow>0</LnbLow>
      <LnbHigh>0</LnbHigh>
      <LnbSwitch>0</LnbSwitch>
    </TuningInfoDvbS>
    <TuningInfoDvbS frequency="3953000000" system="DVB-S" modulation="QPSK" inversion="auto" satnumber="0" symbolrate="3125000" polarity="horizontal" FEC="7/8" rolloff="auto" pilots="auto">
      <LnbLow>0</LnbLow>
      <LnbHigh>0</LnbHigh>
      <LnbSwitch>0</LnbSwitch>
    </TuningInfoDvbS>
    <TuningInfoDvbS frequency="3977000000" system="DVB-S" modulation="QPSK" inversion="auto" satnumber="0" symbolrate="2555000" polarity="horizontal" FEC="3/4" rolloff="auto" pilots="auto">
      <LnbLow>0</LnbLow>
      <LnbHigh>0</LnbHigh>
      <LnbSwitch>0</LnbSwitch>
    </TuningInfoDvbS>
    <TuningInfoDvbS frequency="3980000000" system="DVB-S" modulation="QPSK" inversion="auto" satnumber="0" symbolrate="26470000" polarity="vertical" FEC="5/6" rolloff="auto" pilots="auto">
      <LnbLow>0</LnbLow>
      <LnbHigh>0</LnbHigh>
      <LnbSwitch>0</LnbSwitch>
    </TuningInfoDvbS>
    <TuningInfoDvbS frequency="4000000000" system="DVB-S" modulation="QPSK" inversion="auto" satnumber="0" symbolrate="26400000" polarity="horizontal" FEC="3/4" rolloff="auto" pilots="auto">
      <LnbLow>0</LnbLow>
      <LnbHigh>0</LnbHigh>
      <LnbSwitch>0</LnbSwitch>
    </TuningInfoDvbS>
    <TuningInfoDvbS frequency="4020000000" system="DVB-S2" modulation="QPSK" inversion="auto" satnumber="0" symbolrate="15000000" polarity="vertical" FEC="3/4" rolloff="auto" pilots="auto">
      <LnbLow>0</LnbLow>
      <LnbHigh>0</LnbHigh>
      <LnbSwitch>0</LnbSwitch>
    </TuningInfoDvbS>
    <TuningInfoDvbS frequency="4060000000" system="DVB-S" modulation="QPSK" inversion="auto" satnumber="0" symbolrate="27780000" polarity="vertical" FEC="5/6" rolloff="auto" pilots="auto">
      <LnbLow>0</LnbLow>
      <LnbHigh>0</LnbHigh>
      <LnbSwitch>0</LnbSwitch>
    </TuningInfoDvbS>
    <TuningInfoDvbS frequency="4080000000" system="DVB-S" modulation="QPSK" inversion="auto" satnumber="0" symbolrate="27780000" polarity="horizontal" FEC="5/6" rolloff="auto" pilots="auto">
      <LnbLow>0</LnbLow>
      <LnbHigh>0</LnbHigh>
      <LnbSwitch>0</LnbSwitch>
    </TuningInfoDvbS>
    <TuningInfoDvbS frequency="4120000000" system="DVB-S2" modulation="8-PSK" inversion="auto" satnumber="0" symbolrate="30000000" polarity="horizontal" FEC="9/10" rolloff="auto" pilots="auto">
      <LnbLow>0</LnbLow>
      <LnbHigh>0</LnbHigh>
      <LnbSwitch>0</LnbSwitch>
    </TuningInfoDvbS>
    <TuningInfoDvbS frequency="4140000000" system="DVB-S2" modulation="8-PSK" inversion="auto" satnumber="0" symbolrate="30000000" polarity="vertical" FEC="9/10" rolloff="auto" pilots="auto">
      <LnbLow>0</LnbLow>
      <LnbHigh>0</LnbHigh>
      <LnbSwitch>0</LnbSwitch>
    </TuningInfoDvbS>
    <TuningInfoDvbS frequency="4145000000" system="DVB-S" modulation="QPSK" inversion="auto" satnumber="0" symbolrate="3308000" polarity="horizontal" FEC="3/4" rolloff="auto" pilots="auto">
      <LnbLow>0</LnbLow>
      <LnbHigh>0</LnbHigh>
      <LnbSwitch>0</LnbSwitch>
    </TuningInfoDvbS>
    <TuningInfoDvbS frequency="4193000000" system="DVB-S" modulation="QPSK" inversion="auto" satnumber="0" symbolrate="6620000" polarity="vertical" FEC="2/3" rolloff="auto" pilots="auto">
      <LnbLow>0</LnbLow>
      <LnbHigh>0</LnbHigh>
      <LnbSwitch>0</LnbSwitch>
    </TuningInfoDvbS>
    <TuningInfoDvbS frequency="11771000000" system="DVB-S" modulation="QPSK" inversion="auto" satnumber="0" symbolrate="14321000" polarity="vertical" FEC="3/4" rolloff="auto" pilots="auto">
      <LnbLow>0</LnbLow>
      <LnbHigh>0</LnbHigh>
      <LnbSwitch>0</LnbSwitch>
    </TuningInfoDvbS>
    <TuningInfoDvbS frequency="11782000000" system="DVB-S" modulation="QPSK" inversion="auto" satnumber="0" symbolrate="3979000" polarity="vertical" FEC="3/4" rolloff="auto" pilots="auto">
      <LnbLow>0</LnbLow>
      <LnbHigh>0</LnbHigh>
      <LnbSwitch>0</LnbSwitch>
    </TuningInfoDvbS>
    <TuningInfoDvbS frequency="11787000000" system="DVB-S" modulation="QPSK" inversion="auto" satnumber="0" symbolrate="3979000" polarity="vertical" FEC="3/4" rolloff="auto" pilots="auto">
      <LnbLow>0</LnbLow>
      <LnbHigh>0</LnbHigh>
      <LnbSwitch>0</LnbSwitch>
    </TuningInfoDvbS>
    <TuningInfoDvbS frequency="11792000000" system="DVB-S" modulation="QPSK" inversion="auto" satnumber="0" symbolrate="3979000" polarity="vertical" FEC="3/4" rolloff="auto" pilots="auto">
      <LnbLow>0</LnbLow>
      <LnbHigh>0</LnbHigh>
      <LnbSwitch>0</LnbSwitch>
    </TuningInfoDvbS>
    <TuningInfoDvbS frequency="11800000000" system="DVB-S2" modulation="QPSK" inversion="auto" satnumber="0" symbolrate="30000000" polarity="horizontal" FEC="3/4" rolloff="auto" pilots="auto">
      <LnbLow>0</LnbLow>
      <LnbHigh>0</LnbHigh>
      <LnbSwitch>0</LnbSwitch>
    </TuningInfoDvbS>
    <TuningInfoDvbS frequency="11804000000" system="DVB-S" modulation="QPSK" inversion="auto" satnumber="0" symbolrate="3979000" polarity="vertical" FEC="3/4" rolloff="auto" pilots="auto">
      <LnbLow>0</LnbLow>
      <LnbHigh>0</LnbHigh>
      <LnbSwitch>0</LnbSwitch>
    </TuningInfoDvbS>
    <TuningInfoDvbS frequency="11809000000" system="DVB-S" modulation="QPSK" inversion="auto" satnumber="0" symbolrate="3979000" polarity="vertical" FEC="3/4" rolloff="auto" pilots="auto">
      <LnbLow>0</LnbLow>
      <LnbHigh>0</LnbHigh>
      <LnbSwitch>0</LnbSwitch>
    </TuningInfoDvbS>
    <TuningInfoDvbS frequency="11815000000" system="DVB-S" modulation="QPSK" inversion="auto" satnumber="0" symbolrate="3979000" polarity="vertical" FEC="3/4" rolloff="auto" pilots="auto">
      <LnbLow>0</LnbLow>
      <LnbHigh>0</LnbHigh>
      <LnbSwitch>0</LnbSwitch>
    </TuningInfoDvbS>
    <TuningInfoDvbS frequency="11820000000" system="DVB-S" modulation="QPSK" inversion="auto" satnumber="0" symbolrate="3979000" polarity="vertical" FEC="3/4" rolloff="auto" pilots="auto">
      <LnbLow>0</LnbLow>
      <LnbHigh>0</LnbHigh>
      <LnbSwitch>0</LnbSwitch>
    </TuningInfoDvbS>
    <TuningInfoDvbS frequency="11825000000" system="DVB-S" modulation="QPSK" inversion="auto" satnumber="0" symbolrate="3979000" polarity="vertical" FEC="3/4" rolloff="auto" pilots="auto">
      <LnbLow>0</LnbLow>
      <LnbHigh>0</LnbHigh>
      <LnbSwitch>0</LnbSwitch>
    </TuningInfoDvbS>
    <TuningInfoDvbS frequency="11825000000" system="DVB-S" modulation="QPSK" inversion="auto" satnumber="0" symbolrate="3979000" polarity="horizontal" FEC="3/4" rolloff="auto" pilots="auto">
      <LnbLow>0</LnbLow>
      <LnbHigh>0</LnbHigh>
      <LnbSwitch>0</LnbSwitch>
    </TuningInfoDvbS>
    <TuningInfoDvbS frequency="11830000000" system="DVB-S" modulation="QPSK" inversion="auto" satnumber="0" symbolrate="3979000" polarity="horizontal" FEC="3/4" rolloff="auto" pilots="auto">
      <LnbLow>0</LnbLow>
      <LnbHigh>0</LnbHigh>
      <LnbSwitch>0</LnbSwitch>
    </TuningInfoDvbS>
    <TuningInfoDvbS frequency="11830000000" system="DVB-S" modulation="QPSK" inversion="auto" satnumber="0" symbolrate="3979000" polarity="vertical" FEC="3/4" rolloff="auto" pilots="auto">
      <LnbLow>0</LnbLow>
      <LnbHigh>0</LnbHigh>
      <LnbSwitch>0</LnbSwitch>
    </TuningInfoDvbS>
    <TuningInfoDvbS frequency="11836000000" system="DVB-S" modulation="QPSK" inversion="auto" satnumber="0" symbolrate="3979000" polarity="vertical" FEC="3/4" rolloff="auto" pilots="auto">
      <LnbLow>0</LnbLow>
      <LnbHigh>0</LnbHigh>
      <LnbSwitch>0</LnbSwitch>
    </TuningInfoDvbS>
    <TuningInfoDvbS frequency="11836000000" system="DVB-S" modulation="QPSK" inversion="auto" satnumber="0" symbolrate="3979000" polarity="horizontal" FEC="3/4" rolloff="auto" pilots="auto">
      <LnbLow>0</LnbLow>
      <LnbHigh>0</LnbHigh>
      <LnbSwitch>0</LnbSwitch>
    </TuningInfoDvbS>
    <TuningInfoDvbS frequency="11842000000" system="DVB-S" modulation="QPSK" inversion="auto" satnumber="0" symbolrate="3979000" polarity="horizontal" FEC="3/4" rolloff="auto" pilots="auto">
      <LnbLow>0</LnbLow>
      <LnbHigh>0</LnbHigh>
      <LnbSwitch>0</LnbSwitch>
    </TuningInfoDvbS>
    <TuningInfoDvbS frequency="11848000000" system="DVB-S" modulation="QPSK" inversion="auto" satnumber="0" symbolrate="3979000" polarity="horizontal" FEC="3/4" rolloff="auto" pilots="auto">
      <LnbLow>0</LnbLow>
      <LnbHigh>0</LnbHigh>
      <LnbSwitch>0</LnbSwitch>
    </TuningInfoDvbS>
    <TuningInfoDvbS frequency="11854000000" system="DVB-S" modulation="QPSK" inversion="auto" satnumber="0" symbolrate="3979000" polarity="horizontal" FEC="3/4" rolloff="auto" pilots="auto">
      <LnbLow>0</LnbLow>
      <LnbHigh>0</LnbHigh>
      <LnbSwitch>0</LnbSwitch>
    </TuningInfoDvbS>
    <TuningInfoDvbS frequency="11865000000" system="DVB-S" modulation="QPSK" inversion="auto" satnumber="0" symbolrate="3979000" polarity="horizontal" FEC="3/4" rolloff="auto" pilots="auto">
      <LnbLow>0</LnbLow>
      <LnbHigh>0</LnbHigh>
      <LnbSwitch>0</LnbSwitch>
    </TuningInfoDvbS>
    <TuningInfoDvbS frequency="11871000000" system="DVB-S" modulation="QPSK" inversion="auto" satnumber="0" symbolrate="3979000" polarity="horizontal" FEC="3/4" rolloff="auto" pilots="auto">
      <LnbLow>0</LnbLow>
      <LnbHigh>0</LnbHigh>
      <LnbSwitch>0</LnbSwitch>
    </TuningInfoDvbS>
    <TuningInfoDvbS frequency="11876000000" system="DVB-S" modulation="QPSK" inversion="auto" satnumber="0" symbolrate="3979000" polarity="horizontal" FEC="3/4" rolloff="auto" pilots="auto">
      <LnbLow>0</LnbLow>
      <LnbHigh>0</LnbHigh>
      <LnbSwitch>0</LnbSwitch>
    </TuningInfoDvbS>
    <TuningInfoDvbS frequency="11882000000" system="DVB-S" modulation="QPSK" inversion="auto" satnumber="0" symbolrate="3979000" polarity="horizontal" FEC="3/4" rolloff="auto" pilots="auto">
      <LnbLow>0</LnbLow>
      <LnbHigh>0</LnbHigh>
      <LnbSwitch>0</LnbSwitch>
    </TuningInfoDvbS>
    <TuningInfoDvbS frequency="11884000000" system="DVB-S" modulation="QPSK" inversion="auto" satnumber="0" symbolrate="3979000" polarity="vertical" FEC="3/4" rolloff="auto" pilots="auto">
      <LnbLow>0</LnbLow>
      <LnbHigh>0</LnbHigh>
      <LnbSwitch>0</LnbSwitch>
    </TuningInfoDvbS>
    <TuningInfoDvbS frequency="11888000000" system="DVB-S" modulation="QPSK" inversion="auto" satnumber="0" symbolrate="3979000" polarity="horizontal" FEC="3/4" rolloff="auto" pilots="auto">
      <LnbLow>0</LnbLow>
      <LnbHigh>0</LnbHigh>
      <LnbSwitch>0</LnbSwitch>
    </TuningInfoDvbS>
    <TuningInfoDvbS frequency="11889000000" system="DVB-S" modulation="QPSK" inversion="auto" satnumber="0" symbolrate="3979000" polarity="vertical" FEC="3/4" rolloff="auto" pilots="auto">
      <LnbLow>0</LnbLow>
      <LnbHigh>0</LnbHigh>
      <LnbSwitch>0</LnbSwitch>
    </TuningInfoDvbS>
    <TuningInfoDvbS frequency="11894000000" system="DVB-S" modulation="QPSK" inversion="auto" satnumber="0" symbolrate="3979000" polarity="horizontal" FEC="3/4" rolloff="auto" pilots="auto">
      <LnbLow>0</LnbLow>
      <LnbHigh>0</LnbHigh>
      <LnbSwitch>0</LnbSwitch>
    </TuningInfoDvbS>
    <TuningInfoDvbS frequency="11895000000" system="DVB-S" modulation="QPSK" inversion="auto" satnumber="0" symbolrate="3979000" polarity="vertical" FEC="3/4" rolloff="auto" pilots="auto">
      <LnbLow>0</LnbLow>
      <LnbHigh>0</LnbHigh>
      <LnbSwitch>0</LnbSwitch>
    </TuningInfoDvbS>
    <TuningInfoDvbS frequency="11900000000" system="DVB-S" modulation="QPSK" inversion="auto" satnumber="0" symbolrate="3979000" polarity="vertical" FEC="3/4" rolloff="auto" pilots="auto">
      <LnbLow>0</LnbLow>
      <LnbHigh>0</LnbHigh>
      <LnbSwitch>0</LnbSwitch>
    </TuningInfoDvbS>
    <TuningInfoDvbS frequency="11905000000" system="DVB-S" modulation="QPSK" inversion="auto" satnumber="0" symbolrate="3979000" polarity="horizontal" FEC="3/4" rolloff="auto" pilots="auto">
      <LnbLow>0</LnbLow>
      <LnbHigh>0</LnbHigh>
      <LnbSwitch>0</LnbSwitch>
    </TuningInfoDvbS>
    <TuningInfoDvbS frequency="11905000000" system="DVB-S" modulation="QPSK" inversion="auto" satnumber="0" symbolrate="3979000" polarity="vertical" FEC="3/4" rolloff="auto" pilots="auto">
      <LnbLow>0</LnbLow>
      <LnbHigh>0</LnbHigh>
      <LnbSwitch>0</LnbSwitch>
    </TuningInfoDvbS>
    <TuningInfoDvbS frequency="11910000000" system="DVB-S" modulation="QPSK" inversion="auto" satnumber="0" symbolrate="3979000" polarity="vertical" FEC="3/4" rolloff="auto" pilots="auto">
      <LnbLow>0</LnbLow>
      <LnbHigh>0</LnbHigh>
      <LnbSwitch>0</LnbSwitch>
    </TuningInfoDvbS>
    <TuningInfoDvbS frequency="11911000000" system="DVB-S" modulation="QPSK" inversion="auto" satnumber="0" symbolrate="3979000" polarity="horizontal" FEC="3/4" rolloff="auto" pilots="auto">
      <LnbLow>0</LnbLow>
      <LnbHigh>0</LnbHigh>
      <LnbSwitch>0</LnbSwitch>
    </TuningInfoDvbS>
    <TuningInfoDvbS frequency="11916000000" system="DVB-S" modulation="QPSK" inversion="auto" satnumber="0" symbolrate="3979000" polarity="vertical" FEC="3/4" rolloff="auto" pilots="auto">
      <LnbLow>0</LnbLow>
      <LnbHigh>0</LnbHigh>
      <LnbSwitch>0</LnbSwitch>
    </TuningInfoDvbS>
    <TuningInfoDvbS frequency="11917000000" system="DVB-S" modulation="QPSK" inversion="auto" satnumber="0" symbolrate="3979000" polarity="horizontal" FEC="3/4" rolloff="auto" pilots="auto">
      <LnbLow>0</LnbLow>
      <LnbHigh>0</LnbHigh>
      <LnbSwitch>0</LnbSwitch>
    </TuningInfoDvbS>
    <TuningInfoDvbS frequency="11960000000" system="DVB-S" modulation="QPSK" inversion="auto" satnumber="0" symbolrate="30000000" polarity="horizontal" FEC="7/8" rolloff="auto" pilots="auto">
      <LnbLow>0</LnbLow>
      <LnbHigh>0</LnbHigh>
      <LnbSwitch>0</LnbSwitch>
    </TuningInfoDvbS>
    <TuningInfoDvbS frequency="11980000000" system="DVB-S" modulation="QPSK" inversion="auto" satnumber="0" symbolrate="30000000" polarity="vertical" FEC="5/6" rolloff="auto" pilots="auto">
      <LnbLow>0</LnbLow>
      <LnbHigh>0</LnbHigh>
      <LnbSwitch>0</LnbSwitch>
    </TuningInfoDvbS>
    <TuningInfoDvbS frequency="12020000000" system="DVB-S2" modulation="8-PSK" inversion="auto" satnumber="0" symbolrate="20000000" polarity="vertical" FEC="9/10" rolloff="auto" pilots="auto">
      <LnbLow>0</LnbLow>
      <LnbHigh>0</LnbHigh>
      <LnbSwitch>0</LnbSwitch>
    </TuningInfoDvbS>
    <TuningInfoDvbS frequency="12093000000" system="DVB-S" modulation="QPSK" inversion="auto" satnumber="0" symbolrate="6620000" polarity="horizontal" FEC="3/4" rolloff="auto" pilots="auto">
      <LnbLow>0</LnbLow>
      <LnbHigh>0</LnbHigh>
      <LnbSwitch>0</LnbSwitch>
    </TuningInfoDvbS>
    <TuningInfoDvbS frequency="12100000000" system="DVB-S" modulation="QPSK" inversion="auto" satnumber="0" symbolrate="30000000" polarity="vertical" FEC="5/6" rolloff="auto" pilots="auto">
      <LnbLow>0</LnbLow>
      <LnbHigh>0</LnbHigh>
      <LnbSwitch>0</LnbSwitch>
    </TuningInfoDvbS>
  </Transponders>
  <PositionKey>-992</PositionKey>
  <WesternOffset xsi:nil="true" />
  <EasternOffset xsi:nil="true" />
  <IsCBand>true</IsCBand>
</Satellite>