<?xml version="1.0" encoding="utf-8"?>
<Satellite xmlns:xsi="http://www.w3.org/2001/XMLSchema-instance" xmlns:xsd="http://www.w3.org/2001/XMLSchema">
  <Name />
  <ShortName>108.2E</ShortName>
  <Transponders>
    <TuningInfoDvbS frequency="3483000000" system="DVB-S" modulation="QPSK" inversion="auto" satnumber="0" symbolrate="3000000" polarity="vertical" FEC="3/4" rolloff="auto" pilots="auto">
      <LnbLow>0</LnbLow>
      <LnbHigh>0</LnbHigh>
      <LnbSwitch>0</LnbSwitch>
    </TuningInfoDvbS>
    <TuningInfoDvbS frequency="3552000000" system="DVB-S" modulation="QPSK" inversion="auto" satnumber="0" symbolrate="3100000" polarity="horizontal" FEC="3/4" rolloff="auto" pilots="auto">
      <LnbLow>0</LnbLow>
      <LnbHigh>0</LnbHigh>
      <LnbSwitch>0</LnbSwitch>
    </TuningInfoDvbS>
    <TuningInfoDvbS frequency="3580000000" system="DVB-S2" modulation="8-PSK" inversion="auto" satnumber="0" symbolrate="30000000" polarity="horizontal" FEC="3/4" rolloff="auto" pilots="auto">
      <LnbLow>0</LnbLow>
      <LnbHigh>0</LnbHigh>
      <LnbSwitch>0</LnbSwitch>
    </TuningInfoDvbS>
    <TuningInfoDvbS frequency="3600000000" system="DVB-S2" modulation="8-PSK" inversion="auto" satnumber="0" symbolrate="30000000" polarity="vertical" FEC="3/4" rolloff="auto" pilots="auto">
      <LnbLow>0</LnbLow>
      <LnbHigh>0</LnbHigh>
      <LnbSwitch>0</LnbSwitch>
    </TuningInfoDvbS>
    <TuningInfoDvbS frequency="3620000000" system="DVB-S2" modulation="8-PSK" inversion="auto" satnumber="0" symbolrate="30000000" polarity="horizontal" FEC="3/4" rolloff="auto" pilots="auto">
      <LnbLow>0</LnbLow>
      <LnbHigh>0</LnbHigh>
      <LnbSwitch>0</LnbSwitch>
    </TuningInfoDvbS>
    <TuningInfoDvbS frequency="3640000000" system="DVB-S2" modulation="8-PSK" inversion="auto" satnumber="0" symbolrate="30000000" polarity="vertical" FEC="3/4" rolloff="auto" pilots="auto">
      <LnbLow>0</LnbLow>
      <LnbHigh>0</LnbHigh>
      <LnbSwitch>0</LnbSwitch>
    </TuningInfoDvbS>
    <TuningInfoDvbS frequency="3722000000" system="DVB-S" modulation="QPSK" inversion="auto" satnumber="0" symbolrate="3330000" polarity="horizontal" FEC="3/4" rolloff="auto" pilots="auto">
      <LnbLow>0</LnbLow>
      <LnbHigh>0</LnbHigh>
      <LnbSwitch>0</LnbSwitch>
    </TuningInfoDvbS>
    <TuningInfoDvbS frequency="3732000000" system="DVB-S" modulation="QPSK" inversion="auto" satnumber="0" symbolrate="4160000" polarity="horizontal" FEC="3/4" rolloff="auto" pilots="auto">
      <LnbLow>0</LnbLow>
      <LnbHigh>0</LnbHigh>
      <LnbSwitch>0</LnbSwitch>
    </TuningInfoDvbS>
    <TuningInfoDvbS frequency="3735000000" system="DVB-S" modulation="QPSK" inversion="auto" satnumber="0" symbolrate="1200000" polarity="horizontal" FEC="3/4" rolloff="auto" pilots="auto">
      <LnbLow>0</LnbLow>
      <LnbHigh>0</LnbHigh>
      <LnbSwitch>0</LnbSwitch>
    </TuningInfoDvbS>
    <TuningInfoDvbS frequency="3745000000" system="DVB-S" modulation="QPSK" inversion="auto" satnumber="0" symbolrate="3000000" polarity="horizontal" FEC="3/4" rolloff="auto" pilots="auto">
      <LnbLow>0</LnbLow>
      <LnbHigh>0</LnbHigh>
      <LnbSwitch>0</LnbSwitch>
    </TuningInfoDvbS>
    <TuningInfoDvbS frequency="3776000000" system="DVB-S" modulation="QPSK" inversion="auto" satnumber="0" symbolrate="4280000" polarity="horizontal" FEC="3/4" rolloff="auto" pilots="auto">
      <LnbLow>0</LnbLow>
      <LnbHigh>0</LnbHigh>
      <LnbSwitch>0</LnbSwitch>
    </TuningInfoDvbS>
    <TuningInfoDvbS frequency="3785000000" system="DVB-S" modulation="QPSK" inversion="auto" satnumber="0" symbolrate="4000000" polarity="horizontal" FEC="3/4" rolloff="auto" pilots="auto">
      <LnbLow>0</LnbLow>
      <LnbHigh>0</LnbHigh>
      <LnbSwitch>0</LnbSwitch>
    </TuningInfoDvbS>
    <TuningInfoDvbS frequency="3793000000" system="DVB-S" modulation="QPSK" inversion="auto" satnumber="0" symbolrate="3000000" polarity="horizontal" FEC="3/4" rolloff="auto" pilots="auto">
      <LnbLow>0</LnbLow>
      <LnbHigh>0</LnbHigh>
      <LnbSwitch>0</LnbSwitch>
    </TuningInfoDvbS>
    <TuningInfoDvbS frequency="3797000000" system="DVB-S" modulation="QPSK" inversion="auto" satnumber="0" symbolrate="3905000" polarity="horizontal" FEC="3/4" rolloff="auto" pilots="auto">
      <LnbLow>0</LnbLow>
      <LnbHigh>0</LnbHigh>
      <LnbSwitch>0</LnbSwitch>
    </TuningInfoDvbS>
    <TuningInfoDvbS frequency="3802000000" system="DVB-S" modulation="QPSK" inversion="auto" satnumber="0" symbolrate="3000000" polarity="horizontal" FEC="7/8" rolloff="auto" pilots="auto">
      <LnbLow>0</LnbLow>
      <LnbHigh>0</LnbHigh>
      <LnbSwitch>0</LnbSwitch>
    </TuningInfoDvbS>
    <TuningInfoDvbS frequency="3808000000" system="DVB-S" modulation="QPSK" inversion="auto" satnumber="0" symbolrate="4000000" polarity="horizontal" FEC="3/4" rolloff="auto" pilots="auto">
      <LnbLow>0</LnbLow>
      <LnbHigh>0</LnbHigh>
      <LnbSwitch>0</LnbSwitch>
    </TuningInfoDvbS>
    <TuningInfoDvbS frequency="3812000000" system="DVB-S" modulation="QPSK" inversion="auto" satnumber="0" symbolrate="3000000" polarity="horizontal" FEC="3/4" rolloff="auto" pilots="auto">
      <LnbLow>0</LnbLow>
      <LnbHigh>0</LnbHigh>
      <LnbSwitch>0</LnbSwitch>
    </TuningInfoDvbS>
    <TuningInfoDvbS frequency="3817000000" system="DVB-S" modulation="QPSK" inversion="auto" satnumber="0" symbolrate="3000000" polarity="horizontal" FEC="3/4" rolloff="auto" pilots="auto">
      <LnbLow>0</LnbLow>
      <LnbHigh>0</LnbHigh>
      <LnbSwitch>0</LnbSwitch>
    </TuningInfoDvbS>
    <TuningInfoDvbS frequency="3830000000" system="DVB-S" modulation="QPSK" inversion="auto" satnumber="0" symbolrate="3000000" polarity="horizontal" FEC="3/4" rolloff="auto" pilots="auto">
      <LnbLow>0</LnbLow>
      <LnbHigh>0</LnbHigh>
      <LnbSwitch>0</LnbSwitch>
    </TuningInfoDvbS>
    <TuningInfoDvbS frequency="3890000000" system="DVB-S" modulation="QPSK" inversion="auto" satnumber="0" symbolrate="6000000" polarity="horizontal" FEC="3/4" rolloff="auto" pilots="auto">
      <LnbLow>0</LnbLow>
      <LnbHigh>0</LnbHigh>
      <LnbSwitch>0</LnbSwitch>
    </TuningInfoDvbS>
    <TuningInfoDvbS frequency="3895000000" system="DVB-S" modulation="QPSK" inversion="auto" satnumber="0" symbolrate="2500000" polarity="horizontal" FEC="3/4" rolloff="auto" pilots="auto">
      <LnbLow>0</LnbLow>
      <LnbHigh>0</LnbHigh>
      <LnbSwitch>0</LnbSwitch>
    </TuningInfoDvbS>
    <TuningInfoDvbS frequency="3920000000" system="DVB-S" modulation="QPSK" inversion="auto" satnumber="0" symbolrate="3000000" polarity="horizontal" FEC="3/4" rolloff="auto" pilots="auto">
      <LnbLow>0</LnbLow>
      <LnbHigh>0</LnbHigh>
      <LnbSwitch>0</LnbSwitch>
    </TuningInfoDvbS>
    <TuningInfoDvbS frequency="3947000000" system="DVB-S" modulation="QPSK" inversion="auto" satnumber="0" symbolrate="1500000" polarity="horizontal" FEC="3/4" rolloff="auto" pilots="auto">
      <LnbLow>0</LnbLow>
      <LnbHigh>0</LnbHigh>
      <LnbSwitch>0</LnbSwitch>
    </TuningInfoDvbS>
    <TuningInfoDvbS frequency="3960000000" system="DVB-S" modulation="QPSK" inversion="auto" satnumber="0" symbolrate="3000000" polarity="horizontal" FEC="3/4" rolloff="auto" pilots="auto">
      <LnbLow>0</LnbLow>
      <LnbHigh>0</LnbHigh>
      <LnbSwitch>0</LnbSwitch>
    </TuningInfoDvbS>
    <TuningInfoDvbS frequency="3971000000" system="DVB-S" modulation="QPSK" inversion="auto" satnumber="0" symbolrate="2100000" polarity="horizontal" FEC="3/4" rolloff="auto" pilots="auto">
      <LnbLow>0</LnbLow>
      <LnbHigh>0</LnbHigh>
      <LnbSwitch>0</LnbSwitch>
    </TuningInfoDvbS>
    <TuningInfoDvbS frequency="3981000000" system="DVB-S" modulation="QPSK" inversion="auto" satnumber="0" symbolrate="1235000" polarity="vertical" FEC="3/4" rolloff="auto" pilots="auto">
      <LnbLow>0</LnbLow>
      <LnbHigh>0</LnbHigh>
      <LnbSwitch>0</LnbSwitch>
    </TuningInfoDvbS>
    <TuningInfoDvbS frequency="3990000000" system="DVB-S" modulation="QPSK" inversion="auto" satnumber="0" symbolrate="6000000" polarity="horizontal" FEC="3/4" rolloff="auto" pilots="auto">
      <LnbLow>0</LnbLow>
      <LnbHigh>0</LnbHigh>
      <LnbSwitch>0</LnbSwitch>
    </TuningInfoDvbS>
    <TuningInfoDvbS frequency="3998000000" system="DVB-S" modulation="QPSK" inversion="auto" satnumber="0" symbolrate="3000000" polarity="horizontal" FEC="3/4" rolloff="auto" pilots="auto">
      <LnbLow>0</LnbLow>
      <LnbHigh>0</LnbHigh>
      <LnbSwitch>0</LnbSwitch>
    </TuningInfoDvbS>
    <TuningInfoDvbS frequency="4004000000" system="DVB-S" modulation="QPSK" inversion="auto" satnumber="0" symbolrate="6000000" polarity="horizontal" FEC="3/4" rolloff="auto" pilots="auto">
      <LnbLow>0</LnbLow>
      <LnbHigh>0</LnbHigh>
      <LnbSwitch>0</LnbSwitch>
    </TuningInfoDvbS>
    <TuningInfoDvbS frequency="4014000000" system="DVB-S" modulation="QPSK" inversion="auto" satnumber="0" symbolrate="6000000" polarity="horizontal" FEC="3/4" rolloff="auto" pilots="auto">
      <LnbLow>0</LnbLow>
      <LnbHigh>0</LnbHigh>
      <LnbSwitch>0</LnbSwitch>
    </TuningInfoDvbS>
    <TuningInfoDvbS frequency="4026000000" system="DVB-S" modulation="QPSK" inversion="auto" satnumber="0" symbolrate="1500000" polarity="horizontal" FEC="3/4" rolloff="auto" pilots="auto">
      <LnbLow>0</LnbLow>
      <LnbHigh>0</LnbHigh>
      <LnbSwitch>0</LnbSwitch>
    </TuningInfoDvbS>
    <TuningInfoDvbS frequency="4032000000" system="DVB-S" modulation="QPSK" inversion="auto" satnumber="0" symbolrate="1500000" polarity="horizontal" FEC="3/4" rolloff="auto" pilots="auto">
      <LnbLow>0</LnbLow>
      <LnbHigh>0</LnbHigh>
      <LnbSwitch>0</LnbSwitch>
    </TuningInfoDvbS>
    <TuningInfoDvbS frequency="4036000000" system="DVB-S" modulation="QPSK" inversion="auto" satnumber="0" symbolrate="3100000" polarity="horizontal" FEC="3/4" rolloff="auto" pilots="auto">
      <LnbLow>0</LnbLow>
      <LnbHigh>0</LnbHigh>
      <LnbSwitch>0</LnbSwitch>
    </TuningInfoDvbS>
    <TuningInfoDvbS frequency="4040000000" system="DVB-S" modulation="QPSK" inversion="auto" satnumber="0" symbolrate="3000000" polarity="horizontal" FEC="3/4" rolloff="auto" pilots="auto">
      <LnbLow>0</LnbLow>
      <LnbHigh>0</LnbHigh>
      <LnbSwitch>0</LnbSwitch>
    </TuningInfoDvbS>
    <TuningInfoDvbS frequency="4080000000" system="DVB-S" modulation="QPSK" inversion="auto" satnumber="0" symbolrate="3100000" polarity="horizontal" FEC="3/4" rolloff="auto" pilots="auto">
      <LnbLow>0</LnbLow>
      <LnbHigh>0</LnbHigh>
      <LnbSwitch>0</LnbSwitch>
    </TuningInfoDvbS>
    <TuningInfoDvbS frequency="4086000000" system="DVB-S" modulation="QPSK" inversion="auto" satnumber="0" symbolrate="6000000" polarity="horizontal" FEC="3/4" rolloff="auto" pilots="auto">
      <LnbLow>0</LnbLow>
      <LnbHigh>0</LnbHigh>
      <LnbSwitch>0</LnbSwitch>
    </TuningInfoDvbS>
    <TuningInfoDvbS frequency="4092000000" system="DVB-S" modulation="QPSK" inversion="auto" satnumber="0" symbolrate="3570000" polarity="horizontal" FEC="3/4" rolloff="auto" pilots="auto">
      <LnbLow>0</LnbLow>
      <LnbHigh>0</LnbHigh>
      <LnbSwitch>0</LnbSwitch>
    </TuningInfoDvbS>
    <TuningInfoDvbS frequency="4097000000" system="DVB-S" modulation="QPSK" inversion="auto" satnumber="0" symbolrate="3125000" polarity="horizontal" FEC="3/4" rolloff="auto" pilots="auto">
      <LnbLow>0</LnbLow>
      <LnbHigh>0</LnbHigh>
      <LnbSwitch>0</LnbSwitch>
    </TuningInfoDvbS>
    <TuningInfoDvbS frequency="4130000000" system="DVB-S" modulation="QPSK" inversion="auto" satnumber="0" symbolrate="2100000" polarity="vertical" FEC="3/4" rolloff="auto" pilots="auto">
      <LnbLow>0</LnbLow>
      <LnbHigh>0</LnbHigh>
      <LnbSwitch>0</LnbSwitch>
    </TuningInfoDvbS>
    <TuningInfoDvbS frequency="4159000000" system="DVB-S" modulation="QPSK" inversion="auto" satnumber="0" symbolrate="3000000" polarity="horizontal" FEC="3/4" rolloff="auto" pilots="auto">
      <LnbLow>0</LnbLow>
      <LnbHigh>0</LnbHigh>
      <LnbSwitch>0</LnbSwitch>
    </TuningInfoDvbS>
    <TuningInfoDvbS frequency="11480000000" system="DVB-S2" modulation="8-PSK" inversion="auto" satnumber="0" symbolrate="28800000" polarity="vertical" FEC="2/3" rolloff="auto" pilots="auto">
      <LnbLow>0</LnbLow>
      <LnbHigh>0</LnbHigh>
      <LnbSwitch>0</LnbSwitch>
    </TuningInfoDvbS>
    <TuningInfoDvbS frequency="11481000000" system="DVB-S2" modulation="8-PSK" inversion="auto" satnumber="0" symbolrate="18750000" polarity="horizontal" FEC="3/4" rolloff="auto" pilots="auto">
      <LnbLow>0</LnbLow>
      <LnbHigh>0</LnbHigh>
      <LnbSwitch>0</LnbSwitch>
    </TuningInfoDvbS>
    <TuningInfoDvbS frequency="11483000000" system="DVB-S2" modulation="8-PSK" inversion="auto" satnumber="0" symbolrate="26600000" polarity="horizontal" FEC="3/4" rolloff="auto" pilots="auto">
      <LnbLow>0</LnbLow>
      <LnbHigh>0</LnbHigh>
      <LnbSwitch>0</LnbSwitch>
    </TuningInfoDvbS>
    <TuningInfoDvbS frequency="11510000000" system="DVB-S2" modulation="8-PSK" inversion="auto" satnumber="0" symbolrate="20000000" polarity="horizontal" FEC="3/4" rolloff="auto" pilots="auto">
      <LnbLow>0</LnbLow>
      <LnbHigh>0</LnbHigh>
      <LnbSwitch>0</LnbSwitch>
    </TuningInfoDvbS>
    <TuningInfoDvbS frequency="11520000000" system="DVB-S2" modulation="8-PSK" inversion="auto" satnumber="0" symbolrate="30000000" polarity="vertical" FEC="3/4" rolloff="auto" pilots="auto">
      <LnbLow>0</LnbLow>
      <LnbHigh>0</LnbHigh>
      <LnbSwitch>0</LnbSwitch>
    </TuningInfoDvbS>
    <TuningInfoDvbS frequency="11520000000" system="DVB-S2" modulation="8-PSK" inversion="auto" satnumber="0" symbolrate="30000000" polarity="horizontal" FEC="3/4" rolloff="auto" pilots="auto">
      <LnbLow>0</LnbLow>
      <LnbHigh>0</LnbHigh>
      <LnbSwitch>0</LnbSwitch>
    </TuningInfoDvbS>
    <TuningInfoDvbS frequency="11560000000" system="DVB-S2" modulation="8-PSK" inversion="auto" satnumber="0" symbolrate="30000000" polarity="vertical" FEC="3/4" rolloff="auto" pilots="auto">
      <LnbLow>0</LnbLow>
      <LnbHigh>0</LnbHigh>
      <LnbSwitch>0</LnbSwitch>
    </TuningInfoDvbS>
    <TuningInfoDvbS frequency="11560000000" system="DVB-S2" modulation="8-PSK" inversion="auto" satnumber="0" symbolrate="30000000" polarity="horizontal" FEC="3/4" rolloff="auto" pilots="auto">
      <LnbLow>0</LnbLow>
      <LnbHigh>0</LnbHigh>
      <LnbSwitch>0</LnbSwitch>
    </TuningInfoDvbS>
    <TuningInfoDvbS frequency="11568000000" system="DVB-S2" modulation="8-PSK" inversion="auto" satnumber="0" symbolrate="20000000" polarity="vertical" FEC="3/4" rolloff="auto" pilots="auto">
      <LnbLow>0</LnbLow>
      <LnbHigh>0</LnbHigh>
      <LnbSwitch>0</LnbSwitch>
    </TuningInfoDvbS>
    <TuningInfoDvbS frequency="11568000000" system="DVB-S2" modulation="8-PSK" inversion="auto" satnumber="0" symbolrate="20000000" polarity="horizontal" FEC="3/4" rolloff="auto" pilots="auto">
      <LnbLow>0</LnbLow>
      <LnbHigh>0</LnbHigh>
      <LnbSwitch>0</LnbSwitch>
    </TuningInfoDvbS>
    <TuningInfoDvbS frequency="11598000000" system="DVB-S2" modulation="8-PSK" inversion="auto" satnumber="0" symbolrate="20000000" polarity="vertical" FEC="3/4" rolloff="auto" pilots="auto">
      <LnbLow>0</LnbLow>
      <LnbHigh>0</LnbHigh>
      <LnbSwitch>0</LnbSwitch>
    </TuningInfoDvbS>
    <TuningInfoDvbS frequency="11598000000" system="DVB-S2" modulation="8-PSK" inversion="auto" satnumber="0" symbolrate="20000000" polarity="horizontal" FEC="2/3" rolloff="auto" pilots="auto">
      <LnbLow>0</LnbLow>
      <LnbHigh>0</LnbHigh>
      <LnbSwitch>0</LnbSwitch>
    </TuningInfoDvbS>
    <TuningInfoDvbS frequency="11600000000" system="DVB-S2" modulation="8-PSK" inversion="auto" satnumber="0" symbolrate="30000000" polarity="vertical" FEC="3/4" rolloff="auto" pilots="auto">
      <LnbLow>0</LnbLow>
      <LnbHigh>0</LnbHigh>
      <LnbSwitch>0</LnbSwitch>
    </TuningInfoDvbS>
    <TuningInfoDvbS frequency="11600000000" system="DVB-S2" modulation="8-PSK" inversion="auto" satnumber="0" symbolrate="30000000" polarity="horizontal" FEC="3/4" rolloff="auto" pilots="auto">
      <LnbLow>0</LnbLow>
      <LnbHigh>0</LnbHigh>
      <LnbSwitch>0</LnbSwitch>
    </TuningInfoDvbS>
    <TuningInfoDvbS frequency="11627000000" system="DVB-S2" modulation="8-PSK" inversion="auto" satnumber="0" symbolrate="20000000" polarity="horizontal" FEC="3/4" rolloff="auto" pilots="auto">
      <LnbLow>0</LnbLow>
      <LnbHigh>0</LnbHigh>
      <LnbSwitch>0</LnbSwitch>
    </TuningInfoDvbS>
    <TuningInfoDvbS frequency="11640000000" system="DVB-S2" modulation="8-PSK" inversion="auto" satnumber="0" symbolrate="30000000" polarity="vertical" FEC="3/4" rolloff="auto" pilots="auto">
      <LnbLow>0</LnbLow>
      <LnbHigh>0</LnbHigh>
      <LnbSwitch>0</LnbSwitch>
    </TuningInfoDvbS>
    <TuningInfoDvbS frequency="11640000000" system="DVB-S2" modulation="8-PSK" inversion="auto" satnumber="0" symbolrate="24000000" polarity="horizontal" FEC="3/4" rolloff="auto" pilots="auto">
      <LnbLow>0</LnbLow>
      <LnbHigh>0</LnbHigh>
      <LnbSwitch>0</LnbSwitch>
    </TuningInfoDvbS>
    <TuningInfoDvbS frequency="11656000000" system="DVB-S" modulation="QPSK" inversion="auto" satnumber="0" symbolrate="18750000" polarity="horizontal" FEC="3/4" rolloff="auto" pilots="auto">
      <LnbLow>0</LnbLow>
      <LnbHigh>0</LnbHigh>
      <LnbSwitch>0</LnbSwitch>
    </TuningInfoDvbS>
    <TuningInfoDvbS frequency="11680000000" system="DVB-S2" modulation="8-PSK" inversion="auto" satnumber="0" symbolrate="30000000" polarity="vertical" FEC="3/4" rolloff="auto" pilots="auto">
      <LnbLow>0</LnbLow>
      <LnbHigh>0</LnbHigh>
      <LnbSwitch>0</LnbSwitch>
    </TuningInfoDvbS>
    <TuningInfoDvbS frequency="11685000000" system="DVB-S" modulation="QPSK" inversion="auto" satnumber="0" symbolrate="18750000" polarity="horizontal" FEC="3/4" rolloff="auto" pilots="auto">
      <LnbLow>0</LnbLow>
      <LnbHigh>0</LnbHigh>
      <LnbSwitch>0</LnbSwitch>
    </TuningInfoDvbS>
    <TuningInfoDvbS frequency="12328000000" system="DVB-S" modulation="QPSK" inversion="auto" satnumber="0" symbolrate="5000000" polarity="horizontal" FEC="3/4" rolloff="auto" pilots="auto">
      <LnbLow>0</LnbLow>
      <LnbHigh>0</LnbHigh>
      <LnbSwitch>0</LnbSwitch>
    </TuningInfoDvbS>
    <TuningInfoDvbS frequency="12375000000" system="DVB-S" modulation="QPSK" inversion="auto" satnumber="0" symbolrate="3100000" polarity="vertical" FEC="3/4" rolloff="auto" pilots="auto">
      <LnbLow>0</LnbLow>
      <LnbHigh>0</LnbHigh>
      <LnbSwitch>0</LnbSwitch>
    </TuningInfoDvbS>
    <TuningInfoDvbS frequency="12401000000" system="DVB-S2" modulation="8-PSK" inversion="auto" satnumber="0" symbolrate="2400000" polarity="vertical" FEC="3/4" rolloff="auto" pilots="auto">
      <LnbLow>0</LnbLow>
      <LnbHigh>0</LnbHigh>
      <LnbSwitch>0</LnbSwitch>
    </TuningInfoDvbS>
    <TuningInfoDvbS frequency="12406000000" system="DVB-S" modulation="QPSK" inversion="auto" satnumber="0" symbolrate="3330000" polarity="vertical" FEC="5/6" rolloff="auto" pilots="auto">
      <LnbLow>0</LnbLow>
      <LnbHigh>0</LnbHigh>
      <LnbSwitch>0</LnbSwitch>
    </TuningInfoDvbS>
    <TuningInfoDvbS frequency="12421000000" system="DVB-S" modulation="QPSK" inversion="auto" satnumber="0" symbolrate="2962000" polarity="vertical" FEC="3/4" rolloff="auto" pilots="auto">
      <LnbLow>0</LnbLow>
      <LnbHigh>0</LnbHigh>
      <LnbSwitch>0</LnbSwitch>
    </TuningInfoDvbS>
    <TuningInfoDvbS frequency="12427000000" system="DVB-S" modulation="QPSK" inversion="auto" satnumber="0" symbolrate="4440000" polarity="vertical" FEC="3/4" rolloff="auto" pilots="auto">
      <LnbLow>0</LnbLow>
      <LnbHigh>0</LnbHigh>
      <LnbSwitch>0</LnbSwitch>
    </TuningInfoDvbS>
    <TuningInfoDvbS frequency="12431000000" system="DVB-S" modulation="QPSK" inversion="auto" satnumber="0" symbolrate="30000000" polarity="horizontal" FEC="5/6" rolloff="auto" pilots="auto">
      <LnbLow>0</LnbLow>
      <LnbHigh>0</LnbHigh>
      <LnbSwitch>0</LnbSwitch>
    </TuningInfoDvbS>
    <TuningInfoDvbS frequency="12434000000" system="DVB-S" modulation="QPSK" inversion="auto" satnumber="0" symbolrate="2000000" polarity="horizontal" FEC="3/4" rolloff="auto" pilots="auto">
      <LnbLow>0</LnbLow>
      <LnbHigh>0</LnbHigh>
      <LnbSwitch>0</LnbSwitch>
    </TuningInfoDvbS>
    <TuningInfoDvbS frequency="12439000000" system="DVB-S" modulation="QPSK" inversion="auto" satnumber="0" symbolrate="1900000" polarity="horizontal" FEC="1/2" rolloff="auto" pilots="auto">
      <LnbLow>0</LnbLow>
      <LnbHigh>0</LnbHigh>
      <LnbSwitch>0</LnbSwitch>
    </TuningInfoDvbS>
    <TuningInfoDvbS frequency="12444000000" system="DVB-S" modulation="QPSK" inversion="auto" satnumber="0" symbolrate="1900000" polarity="horizontal" FEC="3/4" rolloff="auto" pilots="auto">
      <LnbLow>0</LnbLow>
      <LnbHigh>0</LnbHigh>
      <LnbSwitch>0</LnbSwitch>
    </TuningInfoDvbS>
    <TuningInfoDvbS frequency="12447000000" system="DVB-S" modulation="QPSK" inversion="auto" satnumber="0" symbolrate="3000000" polarity="horizontal" FEC="3/4" rolloff="auto" pilots="auto">
      <LnbLow>0</LnbLow>
      <LnbHigh>0</LnbHigh>
      <LnbSwitch>0</LnbSwitch>
    </TuningInfoDvbS>
    <TuningInfoDvbS frequency="12471000000" system="DVB-S" modulation="QPSK" inversion="auto" satnumber="0" symbolrate="30000000" polarity="horizontal" FEC="5/6" rolloff="auto" pilots="auto">
      <LnbLow>0</LnbLow>
      <LnbHigh>0</LnbHigh>
      <LnbSwitch>0</LnbSwitch>
    </TuningInfoDvbS>
    <TuningInfoDvbS frequency="12486000000" system="DVB-S" modulation="QPSK" inversion="auto" satnumber="0" symbolrate="2000000" polarity="horizontal" FEC="3/4" rolloff="auto" pilots="auto">
      <LnbLow>0</LnbLow>
      <LnbHigh>0</LnbHigh>
      <LnbSwitch>0</LnbSwitch>
    </TuningInfoDvbS>
    <TuningInfoDvbS frequency="12651000000" system="DVB-S" modulation="QPSK" inversion="auto" satnumber="0" symbolrate="26667000" polarity="vertical" FEC="3/4" rolloff="auto" pilots="auto">
      <LnbLow>0</LnbLow>
      <LnbHigh>0</LnbHigh>
      <LnbSwitch>0</LnbSwitch>
    </TuningInfoDvbS>
    <TuningInfoDvbS frequency="12711000000" system="DVB-S2" modulation="8-PSK" inversion="auto" satnumber="0" symbolrate="30000000" polarity="horizontal" FEC="2/3" rolloff="auto" pilots="auto">
      <LnbLow>0</LnbLow>
      <LnbHigh>0</LnbHigh>
      <LnbSwitch>0</LnbSwitch>
    </TuningInfoDvbS>
    <TuningInfoDvbS frequency="12731000000" system="DVB-S" modulation="QPSK" inversion="auto" satnumber="0" symbolrate="30000000" polarity="vertical" FEC="5/6" rolloff="auto" pilots="auto">
      <LnbLow>0</LnbLow>
      <LnbHigh>0</LnbHigh>
      <LnbSwitch>0</LnbSwitch>
    </TuningInfoDvbS>
  </Transponders>
  <PositionKey>1082</PositionKey>
  <IsCBand>false</IsCBand>
</Satellite>